craftflow/__init__.py
craftflow/core.py
craftflow/nodes.py
craftflow/tools.py
craftflow/examples/__init__.py
craftflow/examples/multi_agent_system.py
craftflow/examples/rag_system.py
craftflow/test/__init__.py
craftflow/test/testCore.py
craftflow/test/testCorev1.py
craftflow/test/testCorev2.py
craftflow/test/testNodes.py
craftflow/test/testNodesv1.py
craftflow/test/testNodesv2.py
craftflow/test/testTool.py
craftflow-1.0.0.dist-info/LICENSE
craftflow-1.0.0.dist-info/METADATA
craftflow-1.0.0.dist-info/WHEEL
craftflow-1.0.0.dist-info/entry_points.txt
craftflow-1.0.0.dist-info/top_level.txt
craftflow-1.0.0.dist-info/RECORD
