Metadata-Version: 2.1
Name: craftflow
Version: 1.0.0
Summary: A powerful workflow orchestration framework
Home-page: https://github.com/scholarlords/CraftFlow
Author: DengHui Zhang
Author-email: zdh13141@gmail.com
Keywords: workflow orchestration async rag agent mcp
Classifier: Development Status :: 5 - Production/Stable
Classifier: Intended Audience :: Developers
Classifier: License :: OSI Approved :: MIT License
Classifier: Programming Language :: Python :: 3.8
Classifier: Programming Language :: Python :: 3.9
Classifier: Programming Language :: Python :: 3.10
Classifier: Programming Language :: Python :: 3.11
Classifier: Topic :: Software Development :: Libraries :: Application Frameworks
Requires-Python: >=3.8
License-File: LICENSE
Provides-Extra: dev
Requires-Dist: pytest ; extra == 'dev'
Requires-Dist: twine ; extra == 'dev'
Requires-Dist: wheel ; extra == 'dev'
